eurepoc/__init__.py
eurepoc/data_cleaning_utils.py
eurepoc/data_query_utils.py
eurepoc/database_query.py
eurepoc/incident_dataframes.py
eurepoc/read_token.py
eurepoc/table_models.py
eurepoc/tables.py
eurepoc_wrapper-0.2.8.dist-info/LICENSE
eurepoc_wrapper-0.2.8.dist-info/METADATA
eurepoc_wrapper-0.2.8.dist-info/WHEEL
eurepoc_wrapper-0.2.8.dist-info/top_level.txt
eurepoc_wrapper-0.2.8.dist-info/RECORD
