Metadata-Version: 2.1
Name: eurepoc_wrapper
Version: 0.2.8
Summary: Wrapper for the EuRepoC API
Author: Camille Borrett, Jonas Hemmelskamp
License: MIT
Project-URL: Documentation, https://eurepoc.readthedocs.io/
Project-URL: Source, https://github.com/jhemmelskamp/eurepoc
Project-URL: Tracker, https://github.com/jhemmelskamp/eurepoc/issues
Project-URL: EuRepoC Project, https://eurepoc.eu/
Requires-Python: >=3.6
License-File: LICENSE
Requires-Dist: requests<3.0.0,>=2.31.0
Requires-Dist: nested_query_string<0.1.0,>=0.0.1
Requires-Dist: pandas<3.0.0,>=2.2.2
Requires-Dist: pydantic<3.0.0,>=2.7.1
